{
    "addons":  {
                   "research-toolkit-v8@niklas.se":  {
                                                         "updates":  [
                                                                         {
                                                                             "version":  "3.14.0",
                                                                             "update_link":  "https://raw.githubusercontent.com/The37thInsight/dbt-thematic-map/main/zotero-research-toolkit/research-toolkit-latest.xpi",
                                                                             "update_hash":  "sha256:402f24879aff03440093bb559c34b76c4f0439ef7638e0d3ee74b0d882015cae",
                                                                             "applications":  {
                                                                                                  "zotero":  {
                                                                                                                 "strict_min_version":  "7.999",
                                                                                                                 "strict_max_version":  "8.0.*"
                                                                                                             }
                                                                                              }
                                                                         }
                                                                     ]
                                                     }
               }
}
